tensorflow_fewshot/__init__.py
tensorflow_fewshot/datasets/__init__.py
tensorflow_fewshot/datasets/meta_dataset.py
tensorflow_fewshot/datasets/meta_dataset_from_array.py
tensorflow_fewshot/datasets/meta_dataset_from_disk.py
tensorflow_fewshot/models/__init__.py
tensorflow_fewshot/models/fast_gradients.py
tensorflow_fewshot/models/maml.py
tensorflow_fewshot/models/prototypical_network.py
tensorflow_fewshot/models/utils.py
tests/__init__.py
tests/datasets/__init__.py
tests/datasets/meta_dataset/__init__.py
tests/datasets/meta_dataset/test_meta_dataset_from_array.py
tests/datasets/meta_dataset/test_meta_dataset_from_directory.py
tests/models/__init__.py
tests/models/test_gradient_utils.py
tests/models/test_maml.py
tests/models/test_prototypical_networks.py
tests/models/test_utils.py
tests/models/theta.py
tensorflow_fewshot-0.0.3.dist-info/LICENSE
tensorflow_fewshot-0.0.3.dist-info/METADATA
tensorflow_fewshot-0.0.3.dist-info/WHEEL
tensorflow_fewshot-0.0.3.dist-info/top_level.txt
tensorflow_fewshot-0.0.3.dist-info/RECORD
